minecraft_learns/__init__.py
minecraft_learns/common.py
minecraft_learns/data.py
minecraft_learns/errors.py
minecraft_learns/graphing.py
minecraft_learns/models/__init__.py
minecraft_learns/models/decision_tree.py
minecraft_learns/models/kmeans.py
minecraft_learns/models/knn.py
minecraft_learns/models/lda.py
minecraft_learns/models/linear_regression.py
minecraft_learns/models/pls.py
minecraft_learns/models/random_forest.py
minecraft_learns/models/svm.py
minecraft_learns/models/generic/__init__.py
minecraft_learns/models/generic/classification_model.py
minecraft_learns/models/generic/model.py
minecraft_learns/models/generic/regression_model.py
tests/__init__.py
tests/test_common.py
tests/test_data.py
tests/test_models.py
minecraft_learns-0.1.0.dist-info/LICENSE
minecraft_learns-0.1.0.dist-info/METADATA
minecraft_learns-0.1.0.dist-info/WHEEL
minecraft_learns-0.1.0.dist-info/top_level.txt
minecraft_learns-0.1.0.dist-info/RECORD
