Metadata-Version: 2.1
Name: minecraft-learns
Version: 0.1.0
Summary: Machine Learning library for Minecraft Education AI interactions
Home-page: https://github.com/Nathan-Nesbitt/Minecraft_Learns
Author: Kathryn Lecha, Nathan Nesbitt
License: UNKNOWN
Platform: UNKNOWN
Requires-Dist: pandas
Requires-Dist: numpy
Requires-Dist: sklearn
Requires-Dist: matplotlib
